[
  {
    "lang": "Indo-Aryan",
    "words": ["vibhitta"],
    "ref": "<div>\u00a0\u00a0\t\t\t<number>11815</number> *<b>vibhitta</b> \u02bb split \u02bc. [Cf. <i>vibhitti</i> -- f. \u02bb splitting \u02bc K\u0101\u1e6dh. - \u221a<smallcaps>bhid</smallcaps>]"
  },
  {
    "lang": "Panj\u0101b\u012b (Pa\u00f1j\u0101b\u012b)",
    "words": [
      "beht"
    ],
    "ref": "kgr. <i>beht</i> m. \u02bb plank \u02bc.</div>"
  },
  {
    "lang": "or kng. K\u0101\u1e45gr\u0101 sub-dialect of \u1e0cogr\u012b dialect of Panj\u0101b\u012b",
    "words": [
      "beht"
    ],
    "ref": "kgr. <i>beht</i> m. \u02bb plank \u02bc.</div>"
  }
]