[
  {
    "lang": "Indo-Aryan",
    "words": ["v\u00edr\u016b\u1e0dha"],
    "ref": "<div>\u00a0\u00a0\t\t\t<number>11871</number> <b>v\u00edr\u016b\u1e0dha</b> \u02bb sprouted \u02bc \u015aBr., <i>vir\u016b\u1e0dhaka</i> -- n. \u02bb grain that has begun to sprout \u02bc Su\u015br. [\u221a<smallcaps>ruh</smallcaps>]"
  },
  {
    "lang": "Pali",
    "words": [
      "vir\u016b\u1e37ha",
      "vir\u016b\u1e37hi"
    ],
    "ref": "Pa. <i>vir\u016b\u1e37ha</i> -- \u02bb growing \u02bc, <i>vir\u016b\u1e37hi</i> -- f. \u02bb growth \u02bc; "
  },
  {
    "lang": "Kumaun\u012b",
    "words": [
      "biru\u1e5b\u0101"
    ],
    "ref": "Ku. <i>biru\u1e5b\u0101</i> \u02bb wheat or pulse first soaked and then fried in oil \u02bc; "
  },
  {
    "lang": "Gujar\u0101t\u012b",
    "words": [
      "varu\u1e5b"
    ],
    "ref": "G. <i>varu\u1e5b</i> n. \u02bb shoots of rice soaked in water \u02bc; "
  },
  {
    "lang": "Mar\u0101\u1e6dh\u012b",
    "words": [
      "vir\u016b\u1e0dh\u1e47\u1ebd",
      "vira\u1e0dh\u0101",
      "vira\u1e0d\u0101",
      "vira\u1e0dh\u012b",
      "\u02da\u1e0dh\u1ebd"
    ],
    "ref": "M. <i>vir\u016b\u1e0dh\u1e47\u1ebd</i> \u02bb to mount, climb, grow vigorously \u02bc, <i>vira\u1e0dh\u0101</i>, <i>vira\u1e0d\u0101</i> m. \u02bb young tree sapling \u02bc, <i>vira\u1e0dh\u012b</i> f., <i>\u02da\u1e0dh\u1ebd</i> n. \u02bb pulse made to sprout by soaking in water \u02bc.</div>"
  }
]