[
  {
    "lang": "Indo-Aryan",
    "words": ["sa\u1e41stabdha"],
    "ref": "<div>\u00a0\u00a0\t\t\t<number>13041</number> <b>sa\u1e41stabdha</b> \u02bb supported \u02bc MBh., \u02bb firm \u02bc Hariv. [Cf. <i>sa\u1e41stabhn\u014dti</i> \u02bb makes firm \u02bc Kau\u015b., Pa. <i>santhambhati</i> \u02bb keeps oneself firm \u02bc. -- \u221a<smallcaps>stambh</smallcaps>]"
  },
  {
    "lang": "Mar\u0101\u1e6dh\u012b",
    "words": [
      "sat\u0101\u1e0d"
    ],
    "ref": "M. <i>sat\u0101\u1e0d</i> \u02bb standing straight, upright \u02bc.</div>"
  }
]