[
  {
    "lang": "Indo-Aryan",
    "words": ["upagraha"],
    "ref": "<div>\u00a0\u00a0\t\t\t<number>2157</number> <b>upagraha</b> m. \u02bb a handful (of ku\u015ba grass) \u02bc K\u0101ty\u015ar. [Cf. <i>upagraha\u1e47a</i> -- n. \u02bb act of seizing \u02bc ib.: \u221a<smallcaps>grah</smallcaps>]"
  },
  {
    "lang": "Prakrit",
    "words": [
      "uvaggaha"
    ],
    "ref": "Pk. <i>uvaggaha</i> -- m. \u02bb seizing \u02bc; "
  },
  {
    "lang": "Gujar\u0101t\u012b",
    "words": [
      "ogh\u0254"
    ],
    "ref": "G. <i>ogh\u0254</i> m. \u02bb bundle of cut crops, stook, bundle of woollen thread \u02bc. -- "
  },
  {
    "lang": "Maithil\u012b",
    "words": [
      "bagah\u0101"
    ],
    "ref": "Mth. (SBhagalpur) <i>bag<superscript>a</superscript>h\u0101</i> \u02bb short rope joining lift rope to bucket of water lift \u02bc?"
  }
]