[
  {
    "lang": "Indo-Aryan",
    "words": ["citth"],
    "ref": "<div>\u00a0\u00a0\t\t\t<number>4802</number> *<b>citth</b> \u02bb pound, tear \u02bc."
  },
  {
    "lang": "Sindh\u012b",
    "words": [
      "citha\u1e47u"
    ],
    "ref": "S. <i>citha\u1e47u</i> \u02bb to pound, bruise, hash \u02bc; "
  },
  {
    "lang": "Lahnd\u0101",
    "words": [
      "cittha\u1e47",
      "citha\u1e47"
    ],
    "ref": "L. <i>cittha\u1e47</i> \u02bb to chew \u02bc, (Ju.) <i>citha\u1e47</i>; "
  },
  {
    "lang": "Panj\u0101b\u012b (Pa\u00f1j\u0101b\u012b)",
    "words": [
      "citth\u1e47\u0101"
    ],
    "ref": "P. <i>citth\u1e47\u0101</i> \u02bb to pound, crush, chew \u02bc; "
  },
  {
    "lang": "Hind\u012b",
    "words": [
      "c\u012bthn\u0101"
    ],
    "ref": "H. <i>c\u012bthn\u0101</i> \u02bb to crush, tear \u02bc; "
  },
  {
    "lang": "Mar\u0101\u1e6dh\u012b",
    "words": [
      "cith\u1e47\u1ebd",
      "\u1e0d"
    ],
    "ref": "M. <i>cith\u1e47\u1ebd</i> \u02bb to take offence \u02bc. -- Ext. with -- <i>\u1e0d</i> -- : "
  },
  {
    "lang": "Sindh\u012b",
    "words": [
      "c\u012btha\u1e5bo",
      "cithi\u1e5ba\u1e47u",
      "cith\u0101\u1e5b\u02da",
      "ceth\u0101\u1e5b\u02da"
    ],
    "ref": "S. <i>c\u012btha\u1e5bo</i> m. \u02bb old ragged clothes \u02bc, <i>cithi\u1e5ba\u1e47u</i>, <i>cith\u0101\u1e5b\u02da</i>, <i>ceth\u0101\u1e5b\u02da</i> \u02bb to bruise, crush \u02bc; "
  },
  {
    "lang": "Panj\u0101b\u012b (Pa\u00f1j\u0101b\u012b)",
    "words": [
      "c\u012bth\u1e5b\u0101"
    ],
    "ref": "P. <i>c\u012bth\u1e5b\u0101</i> m. \u02bb rag \u02bc, "
  },
  {
    "lang": "Kumaun\u012b",
    "words": [
      "cith\u1e5bo"
    ],
    "ref": "Ku. <i>cith\u1e5bo</i>, "
  },
  {
    "lang": "Nep\u0101li",
    "words": [
      "cithro",
      "cithornu"
    ],
    "ref": "N. <i>cithro</i>, <i>cithornu</i> \u02bb to scratch, claw, get scratched \u02bc; "
  },
  {
    "lang": "Hind\u012b",
    "words": [
      "c\u012btha\u1e5b",
      "\u02dath\u1e5b\u0101",
      "cith\u0101\u1e5bn\u0101"
    ],
    "ref": "H. <i>c\u012btha\u1e5b</i>, <i>\u02dath\u1e5b\u0101</i> m. \u02bb rag \u02bc, <i>cith\u0101\u1e5bn\u0101</i> \u02bb to tear to pieces \u02bc; "
  },
  {
    "lang": "Gujar\u0101t\u012b",
    "words": [
      "cith\u1e5bu\u0303",
      "r"
    ],
    "ref": "G. <i>cith\u1e5bu\u0303</i> n. \u02bb rag \u02bc; -- with -- <i>r</i> -- : "
  },
  {
    "lang": "Gujar\u0101t\u012b",
    "words": [
      "cithru\u0303",
      "\u02dar\u012b"
    ],
    "ref": "G. <i>cithru\u0303</i> n., <i>\u02dar\u012b</i> f. \u02bb rag \u02bc.</div>"
  }
]