[
  {
    "lang": "Indo-Aryan",
    "words": ["t\u014dra\u1e47a"],
    "ref": "<div>\u00a0\u00a0\t\t\t<number>5976</number> <b>t\u014dra\u1e47a</b> n. \u02bb arched or festooned doorway \u02bc MBh., \u02bb triangle supporting a large balance \u02bc \u015aivaP."
  },
  {
    "lang": "Pali",
    "words": [
      "t\u014dra\u1e47a"
    ],
    "ref": "Pa. <i>t\u014dra\u1e47a</i> -- n. \u02bb arched doorway \u02bc; "
  },
  {
    "lang": "Prakrit",
    "words": [
      "t\u014dra\u1e47a"
    ],
    "ref": "Pk. <i>t\u014dra\u1e47a</i> -- n. \u02bb outer door, gate \u02bc; "
  },
  {
    "lang": "Mar\u0101\u1e6dh\u012b",
    "words": [
      "tor\u1e47\u1ebd"
    ],
    "ref": "M. <i>tor\u1e47\u1ebd</i> n. \u02bb that part of a waterwheel on which rests the fore -- extremity of the beam and under which the bullock moves \u02bc; "
  },
  {
    "lang": "Sinhalese",
    "words": [
      "tora\u1e47a"
    ],
    "ref": "Si. <i>tora\u1e47a</i> \u02bb arched gateway \u02bc.</div>"
  }
]