[
  {
    "lang": "Indo-Aryan",
    "words": ["p\u0101n\u012byav\u0101ha"],
    "ref": "<div>\u00a0\u00a0\t\t\t<number>8087</number> *<b>p\u0101n\u012byav\u0101ha</b> \u02bb water -- drawer \u02bc. [Cf. <i>jalav\u0101haka</i> -- m. Pa\u00f1cat. -- <smallcaps>p\u0101n\u012b\u02caya -- , v\u0101h\u00e1</smallcaps> -- ]"
  },
  {
    "lang": "Bih\u0101r\u012b",
    "words": [
      "paniw\u0101h"
    ],
    "ref": "Bi. <i>paniw\u0101h</i> \u02bb man who distributes water on field with a shovel \u02bc.</div>"
  }
]