[
  {
    "lang": "Indo-Aryan",
    "words": ["ma\u1e6dha"],
    "ref": "<div>\u00a0\u00a0\t\t\t<number>9727</number> <b>ma\u1e6dha</b><superscript>1</superscript> m. \u02bb hut, cottage, esp. cell of an ascetic \u02bc MBh., <i>ma\u1e6dhik\u0101</i> -- f. Da\u015b. [See <smallcaps>ma\u1e47\u1e0dapa</smallcaps> -- ]"
  },
  {
    "lang": "Prakrit",
    "words": [
      "ma\u1e0dha",
      "\u02da\u1e0dh\u012b"
    ],
    "ref": "Pk. <i>ma\u1e0dha</i> -- m.n., <i>\u02da\u1e0dh\u012b</i> -- f. \u02bb hut \u02bc; "
  },
  {
    "lang": "Kashmiri (K\u0101\u015bm\u012br\u012b)",
    "words": [
      "mar",
      "moru"
    ],
    "ref": "K. <i>mar</i> m. \u02bb hut \u02bc, <i>mor<superscript>u</superscript></i> m. \u02bb dove -- cot, fowl -- house \u02bc; "
  },
  {
    "lang": "Sindh\u012b",
    "words": [
      "ma\u1e5bhu",
      "ma\u1e5bh\u012b"
    ],
    "ref": "S. <i>ma\u1e5bhu</i> m. \u02bb place of residence \u02bc, <i>ma\u1e5bh\u012b</i> f. \u02bb place where an ascetic lives \u02bc; "
  },
  {
    "lang": "Lahnd\u0101",
    "words": [
      "mah\u1e5b\u012b"
    ],
    "ref": "L. <i>mah\u1e5b\u012b</i> f., "
  },
  {
    "lang": "Mult\u0101n\u012b dialect of Lahnd\u0101",
    "words": [
      "ma\u1e5bh\u012b"
    ],
    "ref": "mult. <i>ma\u1e5bh\u012b</i> f. \u02bb small tomb over ashes of a Hindu \u02bc; "
  },
  {
    "lang": "Panj\u0101b\u012b (Pa\u00f1j\u0101b\u012b)",
    "words": [
      "ma\u1e5bh",
      "ma\u1e5bh\u012b"
    ],
    "ref": "P. <i>ma\u1e5bh</i> m., <i>ma\u1e5bh\u012b</i> f. \u02bb monument, tomb \u02bc; "
  },
  {
    "lang": "Kumaun\u012b",
    "words": [
      "ma\u1e5b\u012b",
      "ma\u1e5bul\u012b"
    ],
    "ref": "Ku. <i>ma\u1e5b\u012b</i> f. \u02bb hut \u02bc, <i>ma\u1e5bul\u012b</i> f. \u02bb shed \u02bc; "
  },
  {
    "lang": "Nep\u0101li",
    "words": [
      "mar",
      "h",
      "o"
    ],
    "ref": "N. <i>mar</i>(<i>h</i>)<i>o</i> \u02bb any temporary erection \u02bc; "
  },
  {
    "lang": "Assamese",
    "words": [
      "mar\u0101"
    ],
    "ref": "A. <i>mar\u0101</i> \u02bb tuft of grass at either end of ridgepole of a house \u02bc; "
  },
  {
    "lang": "O\u1e5biy\u0101",
    "words": [
      "ma\u1e5bi\u0101"
    ],
    "ref": "Or. <i>ma\u1e5bi\u0101</i> \u02bb hut \u02bc; "
  },
  {
    "lang": "Bih\u0101r\u012b",
    "words": [
      "mara\u012b",
      "maruk\u0101"
    ],
    "ref": "Bi. <i>mara\u012b</i> \u02bb grass hut \u02bc, (Patna) <i>maruk\u0101</i> \u02bb shed on threshing floor \u02bc; "
  },
  {
    "lang": "Maithil\u012b",
    "words": [
      "ma\u1e5bh\u012b",
      "ma\u1e5bhah\u012b"
    ],
    "ref": "Mth. <i>ma\u1e5bh\u012b</i> \u02bb hut, house \u02bc, <i>ma\u1e5bhah\u012b</i> \u02bb forest hut \u02bc; "
  },
  {
    "lang": "Hind\u012b",
    "words": [
      "ma\u1e5bh\u0101",
      "ma\u1e0dh\u0101",
      "ma\u0303\u1e0dh\u0101",
      "ma\u1e5bh\u012b"
    ],
    "ref": "H. <i>ma\u1e5bh\u0101</i>, <i>ma\u1e0dh\u0101</i>, <i>ma\u0303\u1e0dh\u0101</i> m. \u02bb open hut or shed \u02bc, <i>ma\u1e5bh\u012b</i> f. \u02bb cottage, hut, shed, cell, small temple \u02bc; "
  },
  {
    "lang": "Gujar\u0101t\u012b",
    "words": [
      "ma\u1e0dh",
      "ma\u1e0dh\u012b",
      "\u02da\u1e0dhu\u1e5b\u012b"
    ],
    "ref": "G. <i>ma\u1e0dh</i> m. \u02bb temple \u02bc, <i>ma\u1e0dh\u012b</i>, <i>\u02da\u1e0dhu\u1e5b\u012b</i> f. \u02bb hut \u02bc, "
  },
  {
    "lang": "Mar\u0101\u1e6dh\u012b",
    "words": [
      "ma\u1e0dh",
      "ma\u1e0dh\u012b"
    ],
    "ref": "M. <i>ma\u1e0dh</i> m., <i>ma\u1e0dh\u012b</i> f.; "
  },
  {
    "lang": "Sinhalese",
    "words": [
      "ma\u1e37u -- v\u0101"
    ],
    "ref": "Si. <i>ma\u1e37u -- v\u0101</i> \u02bb hut \u02bc. -- Rather &lt; <smallcaps>ma\u1e47\u1e0dapa</smallcaps> -- : "
  },
  {
    "lang": "Bih\u0101r\u012b",
    "words": [
      "ma\u1e5ba\u012b"
    ],
    "ref": "Bi. (Patna) <i>ma\u1e5ba\u012b</i> \u02bb shed on threshing floor \u02bc; "
  },
  {
    "lang": "Maithil\u012b",
    "words": [
      "ma\u1e5bai\u0101"
    ],
    "ref": "Mth. <i>ma\u1e5bai\u0101</i> \u02bb hut \u02bc."
  }
]