[
  {
    "lang": "Indo-Aryan",
    "words": "\u0101mr\u0101\u1e63\u1e6di",
    "ref": "<html><body><number>1279</number> *<b>\u0101mr\u0101\u1e63\u1e6di</b> \u02bb mango stone \u02bc. [Cf. <i>\u0101mr\u0101sthi</i> -- n. Bhpr. - <smallcaps>\u0101mr\u00e1 -- , a\u1e63\u1e6di</smallcaps> -- ]"
  },
  {
    "lang": "Bih\u0101r\u012b",
    "words": [
      "am\u00e3\u0304\u1e6dh\u012b ke ro\u1e6d\u012b"
    ],
    "ref": "Bi. (Gaya) <i>am\u00e3\u0304\u1e6dh\u012b ke ro\u1e6d\u012b</i> \u02bb bread of crushed mango stones \u02bc."
  }
]