[
  {
    "lang": "Indo-Aryan",
    "words": "handha",
    "ref": "<html><body><number>13970</number> *<b>handha</b> \u02bb place, house \u02bc."
  },
  {
    "lang": "Kalasha (Kal\u00e1\u1e63a \u2014 Dard.)",
    "words": [
      "han",
      "ha\u0304\u0306nd"
    ],
    "ref": "rumb. <i>han</i> (st. <i>ha\u0304\u0306nd</i> -- ) \u02bb house, temple of Je\u1e63\u1e6dak \u02bc, "
  },
  {
    "lang": "Rumb\u016br dialect of Kalasha",
    "words": [
      "han",
      "ha\u0304\u0306nd"
    ],
    "ref": "rumb. <i>han</i> (st. <i>ha\u0304\u0306nd</i> -- ) \u02bb house, temple of Je\u1e63\u1e6dak \u02bc, "
  },
  {
    "lang": "Urtsun dialect of Kalasha",
    "words": [
      "\u0254\u0308\u0304n"
    ],
    "ref": "urt. <i>\u0254\u0308\u0304n</i> \u02bb house \u02bc; "
  },
  {
    "lang": "Sindh\u012b",
    "words": [
      "handhu"
    ],
    "ref": "S. <i>handhu</i> m. \u02bb place, abode, bed, bedding \u02bc (\u2192 "
  },
  {
    "lang": "Bal\u016b\u010d\u012b (Iranian)",
    "words": [
      "hand"
    ],
    "ref": "Bal. <i>hand</i> \u02bb place, dwelling \u02bc)."
  }
]