[
  {
    "lang": "Indo-Aryan",
    "words": "\u0101valgat\u0113",
    "ref": "<html><body><number>1424</number> <b>\u0101valgat\u0113</b> \u02bb springs up \u02bc MBh. [\u221a<smallcaps>valg</smallcaps>]"
  },
  {
    "lang": "Prakrit",
    "words": [
      "\u0101vagga\u1e47a"
    ],
    "ref": "Pk. <i>\u0101vagga\u1e47a</i> -- n. \u02bb springing on a horse \u02bc; "
  },
  {
    "lang": "Mar\u0101\u1e6dh\u012b",
    "words": [
      "\u0101vag\u1e47\u1ebd",
      "av\u02da"
    ],
    "ref": "M. <i>\u0101vag\u1e47\u1ebd</i>, <i>av\u02da</i> \u02bb to run wild \u02bc -- Bloch LM 293. <p></p></body></html>"
  }
]