[
  {
    "lang": "Indo-Aryan",
    "words": "\u0101nt\u00e1m",
    "ref": "<html><body><number>14270</number> \u2020<b>\u0101nt\u00e1m</b> \u02bb to the end, completely, head to foot \u02bc TS., \u015aBr. [<smallcaps>\u0101, \u00e1nta</smallcaps> -- ]"
  },
  {
    "lang": "Kashmiri (K\u0101\u015bm\u012br\u012b)",
    "words": [
      "\u00f4tu",
      "\u0101\u0301ntaka",
      "\u00f5\u02c5du"
    ],
    "ref": "K. <i>\u00f4t<superscript>u</superscript></i> m. \u02bb end of bottomlessness, depth or deepness of anything, shallowness of anything \u02bc (&lt; *<i>\u0101\u0301ntaka</i> -- ? But why not *<i>\u00f5\u02c5d<superscript>u</superscript></i>?)."
  }
]