[
  {
    "lang": "Indo-Aryan",
    "words": "dh\u00e1nu -- 2.",
    "ref": "<html><body><number>14642</number> <b>dh\u00e1nu -- <superscript>2</superscript>.</b> 2. <b>dh\u00e1nvan -- <superscript>2</superscript>:</b> Kt. <i>d\u00fam\u0259</i> \u02bb waterless place \u02bc, <i>dum\u0101</i> \u02bb dry (crops) \u02bc, <i>d\u0259m -- \u01f0al\u00e4\u00ed</i> \u02bb a kind of duck living on land \u02bc, (Davidson) <i>dam -- kol -- w\u0101</i> \u02bb in a dry year \u02bc."
  },
  {
    "lang": "Kalasha (Kal\u00e1\u1e63a \u2014 Dard.)",
    "words": [
      "th"
    ],
    "ref": "urt. <i>th</i> -- \u2190 "
  },
  {
    "lang": "Urtsun dialect of Kalasha",
    "words": [
      "th"
    ],
    "ref": "urt. <i>th</i> -- \u2190 "
  },
  {
    "lang": "Rumb\u016br dialect of Kalasha",
    "words": [
      "dh",
      "th"
    ],
    "ref": "rumb. (in which <i>dh</i> -- &gt; <i>th</i>&lt;-&gt; is regular) rather than due to "
  }
]