[
  {
    "lang": "Indo-Aryan",
    "words": "adhunaiva",
    "ref": "<html><body><number>270</number> <b>adhunaiva</b> \u02bb just now \u02bc. [<smallcaps>adhun\u0101\u02ca, \u0113v\u00e1</smallcaps><superscript>1</superscript>]"
  },
  {
    "lang": "Kashmiri (K\u0101\u015bm\u012br\u012b)",
    "words": [
      "wu\u00f1e\u0306",
      "wu\u00f1"
    ],
    "ref": "K. <i>wu\u00f1e\u0306</i>, <i>wu\u00f1</i> \u02bb at this very time \u02bc; "
  },
  {
    "lang": "Lahnd\u0101",
    "words": [
      "hu\u1e47\u1ebd"
    ],
    "ref": "L. <i>hu\u1e47\u1ebd</i> \u02bb just now \u02bc; "
  },
  {
    "lang": "Panj\u0101b\u012b (Pa\u00f1j\u0101b\u012b)",
    "words": [
      "hu\u1e47e"
    ],
    "ref": "P. <i>hu\u1e47e</i> \u02bb immediately \u02bc. <p></p></body></html>"
  }
]