[
  {
    "lang": "Indo-Aryan",
    "words": "k\u0101\u1e6da",
    "ref": "<html><body><number>3017</number> *<b>k\u0101\u1e6da</b><superscript>2</superscript> \u02bb stick, penis \u02bc. [Cf. *<smallcaps>ka\u1e47\u1e6da</smallcaps> -- <superscript>3</superscript>]"
  },
  {
    "lang": "Pali",
    "words": [
      "k\u0101\u1e6da -- k\u014d\u1e6dacik\u0101"
    ],
    "ref": "Pa. <i>k\u0101\u1e6da -- k\u014d\u1e6dacik\u0101</i> -- \u02bb penis and vulva (as term of abuse) \u02bc; "
  },
  {
    "lang": "Gypsy or Romani",
    "words": [
      "kar",
      "karor\u00f3"
    ],
    "ref": "eur. <i>kar</i> m. \u02bb penis \u02bc, <i>karor\u00f3</i> m. \u02bb small do. \u02bc, "
  },
  {
    "lang": "European (Gypsy)",
    "words": [
      "kar",
      "karor\u00f3"
    ],
    "ref": "eur. <i>kar</i> m. \u02bb penis \u02bc, <i>karor\u00f3</i> m. \u02bb small do. \u02bc, "
  },
  {
    "lang": "Sindh\u012b",
    "words": [
      "k\u0101\u1e5bu"
    ],
    "ref": "S. <i>k\u0101\u1e5bu</i> m., "
  },
  {
    "lang": "Hind\u012b",
    "words": [
      "k\u0101\u1e5bh"
    ],
    "ref": "H. <i>k\u0101\u1e5bh</i> m., "
  },
  {
    "lang": "Gujar\u0101t\u012b",
    "words": [
      "k\u0101\u1e5b"
    ],
    "ref": "G. <i>k\u0101\u1e5b</i> m.; "
  },
  {
    "lang": "Mar\u0101\u1e6dh\u012b",
    "words": [
      "k\u0101\u1e0d",
      "k\u0101\u1e0d\u012b",
      "k\u0101\u1e0d\u016bk"
    ],
    "ref": "M. <i>k\u0101\u1e0d</i> n. f. \u02bb straw \u02bc, <i>k\u0101\u1e0d\u012b</i> f. \u02bb little stick, blade of grass \u02bc, <i>k\u0101\u1e0d\u016bk</i> n. \u02bb little stick \u02bc.<div>\u00a0\u00a0\t\t\t</div></body></html>"
  }
]