[
  {
    "lang": "Indo-Aryan",
    "words": "g\u0113hadv\u0101ra",
    "ref": "<html><body><number>4252</number> *<b>g\u0113hadv\u0101ra</b> \u02bb house -- door \u02bc. [<smallcaps>g\u0113h\u00e1 -- , dv\u0101\u02cara</smallcaps> -- ]"
  },
  {
    "lang": "Pali",
    "words": [
      "g\u0113hadv\u0101ra"
    ],
    "ref": "Pa. <i>g\u0113hadv\u0101ra</i> -- n. \u02bb house -- door \u02bc; "
  },
  {
    "lang": "Sinhalese",
    "words": [
      "gedara"
    ],
    "ref": "Si. <i>gedara</i> \u02bb a house with its premises, home \u02bc. -- See *<smallcaps>gharadv\u0101ra</smallcaps> -- .<div>\u00a0\u00a0\t\t\t</div></body></html>"
  }
]