[
  {
    "lang": "Indo-Aryan",
    "words": "jh\u012byat\u0113",
    "ref": "<html><body><number>5396</number> *<b>jh\u012byat\u0113</b> \u02bb wastes away \u02bc. [~ <smallcaps>k\u1e63\u012by\u00e1t\u0113. -- \u221a*jhi</smallcaps>]"
  },
  {
    "lang": "Prakrit",
    "words": [
      "jhijja\u00ef"
    ],
    "ref": "Pk. <i>jhijja\u00ef</i> \u02bb wastes away \u02bc, "
  },
  {
    "lang": "Hind\u012b",
    "words": [
      "jh\u012bjhn\u0101"
    ],
    "ref": "H. <i>jh\u012bjhn\u0101</i>, "
  },
  {
    "lang": "Mar\u0101\u1e6dh\u012b",
    "words": [
      "jhij\u0308\u1e47\u1ebd"
    ],
    "ref": "M. <i>jhij\u0308\u1e47\u1ebd</i>; -- "
  },
  {
    "lang": "Nep\u0101li",
    "words": [
      "jhijo"
    ],
    "ref": "N. <i>jhijo</i> \u02bb worry, care \u02bc. -- Phonet. derivation from <smallcaps>jh\u012bryati</smallcaps> is possible, but in view of *<smallcaps>jh\u012bna</smallcaps> -- and the equivalence of <smallcaps>k\u1e63\u012by\u00e1t\u0113</smallcaps> is less likely.<div>\u00a0\u00a0\t\t\t</div></body></html>"
  }
]