[
  {
    "lang": "Indo-Aryan",
    "words": "\u00e1rdhika",
    "ref": "<html><body><number>682</number> <b>\u00e1rdhika</b> \u02bb measuring half \u02bc Y\u0101j\u00f1., \u02bb forming half of \u02bc Mn., \u02bb receiving half the crop \u02bc Vi\u1e63\u1e47us. [Cf. <i>ardh\u00edn</i> -- \u02bb forming a half \u02bc TS., \u02bb receiving a half \u02bc Mn.: <smallcaps>ardh\u00e1</smallcaps> -- <superscript>2</superscript>]"
  },
  {
    "lang": "Kumaun\u012b",
    "words": [
      "adhiy\u0101"
    ],
    "ref": "Ku. <i>adhiy\u0101</i> \u02bb half the crop paid as rent \u02bc; "
  },
  {
    "lang": "Nep\u0101li",
    "words": [
      "adhiy\u0101"
    ],
    "ref": "N. <i>adhiy\u0101</i> \u02bb equal partnership \u02bc; "
  },
  {
    "lang": "Assamese",
    "words": [
      "\u0101dhi"
    ],
    "ref": "A. <i>\u0101dhi</i> \u02bb half share of the produce of land let to another \u02bc; "
  },
  {
    "lang": "Bih\u0101r\u012b",
    "words": [
      "adhiy\u0101"
    ],
    "ref": "Bi. <i>adhiy\u0101</i> \u02bb the method of thus dividing the crop \u02bc, "
  },
  {
    "lang": "Hind\u012b",
    "words": [
      "\u0101dhy\u0101",
      "adhiy\u0101",
      "adhy\u0101"
    ],
    "ref": "H. <i>\u0101dhy\u0101</i>, <i>adhiy\u0101</i>, <i>adhy\u0101</i> f."
  }
]