[
  {
    "lang": "Indo-Aryan",
    "words": "p\u012btamr\u0325dik\u0101",
    "ref": "<html><body><number>8232</number> *<b>p\u012btamr\u0325dik\u0101</b> \u02bb yellow earth \u02bc. [<smallcaps>p\u012bta -- <superscript>2</superscript>, m\u0155\u030ad</smallcaps> -- <superscript>2</superscript>]"
  },
  {
    "lang": "Kashmiri (K\u0101\u015bm\u012br\u012b)",
    "words": [
      "piv\u00fcr\u00fc"
    ],
    "ref": "K. <i>piv<superscript>\u00fc</superscript>r<superscript>\u00fc</superscript></i> f. \u02bb a kind of yellow earth used for colourwash on walls \u02bc; "
  },
  {
    "lang": "Sindh\u012b",
    "words": [
      "pevi\u1e5b\u012b"
    ],
    "ref": "S. <i>pevi\u1e5b\u012b</i> f. \u02bb a kind of yellow colour or dye \u02bc; "
  },
  {
    "lang": "Panj\u0101b\u012b (Pa\u00f1j\u0101b\u012b)",
    "words": [
      "peor\u012b"
    ],
    "ref": "P. <i>peor\u012b</i> f. \u02bb a precipitate dried from urine of cows fed on mango leaves \u02bc; "
  },
  {
    "lang": "Assamese",
    "words": [
      "p\u1ebduri"
    ],
    "ref": "A. <i>p\u1ebduri</i> \u02bb a yellow substance for painting women's foreheads \u02bc; "
  },
  {
    "lang": "Bengali (Ba\u1e45gl\u0101)",
    "words": [
      "piu\u1e5bi"
    ],
    "ref": "B. <i>piu\u1e5bi</i> \u02bb yellow ochre, yellowish colour \u02bc; "
  },
  {
    "lang": "Hind\u012b",
    "words": [
      "piy\u016b\u1e5b\u012b",
      "pew\u1e5b\u012b"
    ],
    "ref": "H. <i>piy\u016b\u1e5b\u012b</i>, <i>pew\u1e5b\u012b</i> f. \u02bb yellow chalk \u02bc; "
  },
  {
    "lang": "Mar\u0101\u1e6dh\u012b",
    "words": [
      "piv\u1e0d\u012b",
      "pev\u1e0d\u012b"
    ],
    "ref": "M. <i>piv\u1e0d\u012b</i>, <i>pev\u1e0d\u012b</i> f. \u02bb a yellow pigment \u02bc.<div>\u00a0\u00a0\t\t\t</div></body></html>"
  }
]