[
  {
    "lang": "Indo-Aryan",
    "words": "praghar\u1e63ati",
    "ref": "<html><body><number>8483</number> <b>praghar\u1e63ati</b> \u02bb rubs to pieces \u02bc Kau\u015b. [\u221a<smallcaps>ghr\u0325\u1e63</smallcaps>]"
  },
  {
    "lang": "Prakrit",
    "words": [
      "pagha\u1e41sa\u00ef",
      "\u02dasa\u1e47a"
    ],
    "ref": "Pk. <i>pagha\u1e41sa\u00ef</i>, <i>\u02dasa\u1e47a</i> -- n. \u02bb rubbing again and again \u02bc; "
  },
  {
    "lang": "Sinhalese",
    "words": [
      "p\u0101sinav\u0101",
      "p\u0101hi\u02da"
    ],
    "ref": "Si. <i>p\u0101sinav\u0101</i>, <i>p\u0101hi\u02da</i> \u02bb to pound, clean rice by pounding, grind, bruise, cut \u02bc."
  }
]