[
  {
    "lang": "Indo-Aryan",
    "words": "pratigamana",
    "ref": "<html><body><number>8552</number> <b>pratigamana</b> n. \u02bb return \u02bc R. [Cf. <i>praty\u0101gamana</i> -- n. \u02bb coming home again \u02bc MBh., <i>pr\u00e1tigacchati</i> \u02bb goes to meet \u02bc RV., \u02bb goes home \u02bc MBh., Pa. <i>pa\u1e6digacchati g\u0113ha\u1e41</i> \u02bb leaves one's home \u02bc. -- \u221a<smallcaps>gam</smallcaps>]"
  },
  {
    "lang": "Prakrit",
    "words": [
      "pa\u1e0digama\u1e47a"
    ],
    "ref": "Pk. <i>pa\u1e0digama\u1e47a</i> -- n. \u02bb turning back \u02bc; "
  },
  {
    "lang": "Kumaun\u012b",
    "words": [
      "pal\u016b\u1e47"
    ],
    "ref": "Ku. <i>pal\u016b\u1e47</i> \u02bb the second going of the bride to husband's house \u02bc. <p></p></body></html>"
  }
]