[
  {
    "lang": "Indo-Aryan",
    "words": "pratilla",
    "ref": "<html><body><number>8594</number> *<b>pratilla</b> \u02bb opposite \u02bc. [<smallcaps>pr\u00e1ti</smallcaps>]"
  },
  {
    "lang": "Hind\u012b",
    "words": [
      "pail\u0101r"
    ],
    "ref": "H. <i>pail\u0101r</i> adv. \u02bb beyond \u02bc; "
  },
  {
    "lang": "Gujar\u0101t\u012b",
    "words": [
      "pelu\u0303"
    ],
    "ref": "G. <i>pelu\u0303</i> \u02bb that, yonder \u02bc; "
  },
  {
    "lang": "Mar\u0101\u1e6dh\u012b",
    "words": [
      "pail",
      "pail\u0101"
    ],
    "ref": "M. <i>pail</i> \u02bb opposite \u02bc, <i>pail\u0101</i> \u02bb coming from the other bank \u02bc LM 371 (but rather &lt; <smallcaps>pratik\u016b\u0301la</smallcaps> -- ).<div>\u00a0\u00a0\t\t\t</div></body></html>"
  }
]