[
  {
    "lang": "Indo-Aryan",
    "words": "pravaya\u1e47a",
    "ref": "<html><body><number>8783</number> <b>pravaya\u1e47a</b><superscript>1</superscript> m. (n. lex.) \u02bb goad \u02bc P\u0101\u1e47. [\u221a<smallcaps>v\u012b</smallcaps>]"
  },
  {
    "lang": "Prakrit",
    "words": [
      "pavaya\u1e47a"
    ],
    "ref": "Pk. <i>pavaya\u1e47a</i> -- m. \u02bb whip \u02bc; "
  },
  {
    "lang": "Panj\u0101b\u012b (Pa\u00f1j\u0101b\u012b)",
    "words": [
      "paren",
      "prat\u012bk\u1e63\u1e47a"
    ],
    "ref": "kgr. <i>paren</i> m. \u02bb ox -- goad \u02bc (ND 371 b 12 wrongly &lt; *<i>prat\u012bk\u1e63\u1e47a</i> -- ); "
  },
  {
    "lang": "or kng. K\u0101\u1e45gr\u0101 sub-dialect of \u1e0cogr\u012b dialect of Panj\u0101b\u012b",
    "words": [
      "paren",
      "prat\u012bk\u1e63\u1e47a"
    ],
    "ref": "kgr. <i>paren</i> m. \u02bb ox -- goad \u02bc (ND 371 b 12 wrongly &lt; *<i>prat\u012bk\u1e63\u1e47a</i> -- ); "
  },
  {
    "lang": "Bih\u0101r\u012b",
    "words": [
      "paen\u0101",
      "pain\u0101",
      "pen\u0101"
    ],
    "ref": "Bi. <i>paen\u0101</i>, <i>pain\u0101</i>, <i>pen\u0101</i> \u02bb bamboo ox -- whip \u02bc; "
  },
  {
    "lang": "Maithil\u012b",
    "words": [
      "pain\u0101"
    ],
    "ref": "Mth. <i>pain\u0101</i> \u02bb whip or goad for cattle \u02bc; "
  },
  {
    "lang": "Hind\u012b",
    "words": [
      "pain\u0101"
    ],
    "ref": "H. <i>pain\u0101</i> m. \u02bb goad \u02bc. -- "
  },
  {
    "lang": "Gujar\u0101t\u012b",
    "words": [
      "par\u0254\u1e47\u0254",
      "\u02da\u1e47\u012b",
      "\u0254",
      "a\u014d"
    ],
    "ref": "G. <i>par\u0254\u1e47\u0254</i> m., <i>\u02da\u1e47\u012b</i> f. \u02bb goad \u02bc more prob. &lt; *<smallcaps>prat\u014ddana</smallcaps> -- (with -- <i>\u0254</i> -- &lt; -- <i>a\u014d</i> -- ).<div>\u00a0\u00a0\t\t\t</div></body></html>"
  }
]