[
  {
    "lang": "Indo-Aryan",
    "words": "pru\u1e63yati",
    "ref": "<html><body><number>8987</number> *<b>pru\u1e63yati</b><superscript>1</superscript> \u02bb is wet \u02bc. [<i>v\u00edpru\u1e63yati</i> \u02bb oozes out \u02bc \u015aBr. - \u221a<smallcaps>pru\u1e63</smallcaps><superscript>1</superscript>]"
  },
  {
    "lang": "Lahnd\u0101",
    "words": [
      "pussa\u1e47",
      "puss\u012b"
    ],
    "ref": "L. <i>pussa\u1e47</i> \u02bb to be wetted \u02bc, <i>puss\u012b</i> f. \u02bb moisture, hot fomentation \u02bc (&lt; "
  },
  {
    "lang": "Middle Indo-aryan",
    "words": [
      "pussia"
    ],
    "ref": "MIA. pp. *<i>pussia</i> -- ?). <p></p></body></html>"
  }
]