[
  {
    "lang": "Indo-Aryan",
    "words": "ph\u014dssa",
    "ref": "<html><body><number>9114</number> *<b>ph\u014dssa</b> \u02bb hollow \u02bc. [See list s.v. *<smallcaps>p\u014dka</smallcaps> -- ]"
  },
  {
    "lang": "Assamese",
    "words": [
      "ph\u00f5h\u0101"
    ],
    "ref": "A. <i>ph\u00f5h\u0101</i> \u02bb blister \u02bc; -- "
  },
  {
    "lang": "Dameli (Dam\u03b5\u0303\u1e0d\u012b\u02ca \u2014 Kaf.-Dard.)",
    "words": [
      "ph\u014ds\u012b\u0301ra"
    ],
    "ref": "Dm. <i>ph\u014ds\u012b\u0301ra</i> \u02bb rotten \u02bc; &lt;-&gt; "
  },
  {
    "lang": "Panj\u0101b\u012b (Pa\u00f1j\u0101b\u012b)",
    "words": [
      "phosa\u1e5b"
    ],
    "ref": "P. <i>phosa\u1e5b</i> m. \u02bb idle fellow \u02bc; "
  },
  {
    "lang": "Nep\u0101li",
    "words": [
      "phosro"
    ],
    "ref": "N. <i>phosro</i> \u02bb empty, useless \u02bc; &lt;-&gt; "
  },
  {
    "lang": "Bengali (Ba\u1e45gl\u0101)",
    "words": [
      "phosk\u0101"
    ],
    "ref": "H. <i>phosk\u0101</i> m. \u02bb blister \u02bc. <p><b>BA\u1e40H</b> \u02bb be big \u02bc: <smallcaps>bahala -- , bah\u00fa -- , b\u0101\u1e0dh\u00e1</smallcaps> -- .</p> <p></p></body></html>"
  },
  {
    "lang": "Hind\u012b",
    "words": [
      "phosk\u0101"
    ],
    "ref": "H. <i>phosk\u0101</i> m. \u02bb blister \u02bc. <p><b>BA\u1e40H</b> \u02bb be big \u02bc: <smallcaps>bahala -- , bah\u00fa -- , b\u0101\u1e0dh\u00e1</smallcaps> -- .</p> <p></p></body></html>"
  }
]