[
  {
    "lang": "Indo-Aryan",
    "words": "bha\u00f1jati,",
    "ref": "<html><body><number>9363</number> *<b>bha\u00f1jati,</b> <i>bhan\u00e1kti</i>, pl. <i>bha\u00f1j\u00e1nti</i> \u02bb breaks \u02bc RV. [\u221a<smallcaps>bha\u00f1j</smallcaps>]"
  },
  {
    "lang": "Pali",
    "words": [
      "bha\u00f1jati"
    ],
    "ref": "Pa. <i>bha\u00f1jati</i>; "
  },
  {
    "lang": "Prakrit",
    "words": [
      "bha\u1e41ja\u00ef",
      "bha\u1e41jia"
    ],
    "ref": "Pk. <i>bha\u1e41ja\u00ef</i> \u02bb breaks \u02bc, <i>bha\u1e41jia</i> -- \u02bb fled \u02bc, "
  },
  {
    "lang": "Phal\u016b\u1e5ba (Dard.)",
    "words": [
      "bhan\u01f0\u016b\u0301m"
    ],
    "ref": "Phal. <i>bhan\u01f0\u016b\u0301m</i> \u02bb I beat \u02bc; "
  },
  {
    "lang": "Sindh\u012b",
    "words": [
      "bha\u00f1a\u1e47u"
    ],
    "ref": "S. <i>bha\u00f1a\u1e47u</i> \u02bb to break, split \u02bc; "
  },
  {
    "lang": "Kumaun\u012b",
    "words": [
      "bh\u00e3\u0304c\u1e47o"
    ],
    "ref": "Ku. <i>bh\u00e3\u0304c\u1e47o</i> \u02bb to turn a metal article into another shape \u02bc, "
  },
  {
    "lang": "Ga\u1e45go\u012b dialect of Kumaun\u012b",
    "words": [
      "bh\u00e3\u0304cnu",
      "c",
      "bh\u00e3\u0304jcha",
      "bh\u00e3\u0304ccha"
    ],
    "ref": "N. <i>bh\u00e3\u0304cnu</i> (<i>c</i> from *<i>bh\u00e3\u0304jcha</i> &amp;c. &gt; <i>bh\u00e3\u0304ccha</i>?); "
  },
  {
    "lang": "Nep\u0101li",
    "words": [
      "bh\u00e3\u0304cnu",
      "c",
      "bh\u00e3\u0304jcha",
      "bh\u00e3\u0304ccha"
    ],
    "ref": "N. <i>bh\u00e3\u0304cnu</i> (<i>c</i> from *<i>bh\u00e3\u0304jcha</i> &amp;c. &gt; <i>bh\u00e3\u0304ccha</i>?); "
  },
  {
    "lang": "Bengali (Ba\u1e45gl\u0101)",
    "words": [
      "bh\u00e3\u0304j\u0101"
    ],
    "ref": "B. <i>bh\u00e3\u0304j\u0101</i> \u02bb to fold \u02bc; "
  },
  {
    "lang": "O\u1e5biy\u0101",
    "words": [
      "bh\u0101\u00f1jib\u0101"
    ],
    "ref": "Or. <i>bh\u0101\u00f1jib\u0101</i> \u02bb to break in pieces, fold \u02bc, intr. \u02bb to flee \u02bc; "
  },
  {
    "lang": "Bhojpur\u012b",
    "words": [
      "bh\u00e3\u0304jal"
    ],
    "ref": "Bhoj. <i>bh\u00e3\u0304jal</i> \u02bb to fold \u02bc; "
  },
  {
    "lang": "Hind\u012b",
    "words": [
      "bh\u00e3\u0304jn\u0101",
      "bha\u0303jn\u0101"
    ],
    "ref": "H. <i>bh\u00e3\u0304jn\u0101</i> \u02bb to break, twist, turn \u02bc (whence intr. <i>bha\u0303jn\u0101</i> \u02bb to be divided \u02bc); "
  },
  {
    "lang": "Gujar\u0101t\u012b",
    "words": [
      "bh\u00e3\u0304jvu\u0303"
    ],
    "ref": "G. <i>bh\u00e3\u0304jvu\u0303</i> \u02bb to break \u02bc; "
  },
  {
    "lang": "Mar\u0101\u1e6dh\u012b",
    "words": [
      "bh\u00e3\u0304j\u0308\u1e47\u1ebd"
    ],
    "ref": "M. <i>bh\u00e3\u0304j\u0308\u1e47\u1ebd</i> \u02bb to distribute \u02bc; -- "
  },
  {
    "lang": "Prakrit",
    "words": [
      "bha\u1e41j\u0101via"
    ],
    "ref": "Pk. <i>bha\u1e41j\u0101via</i> -- \u02bb put to flight \u02bc; "
  },
  {
    "lang": "Nep\u0101li",
    "words": [
      "bha\u0303j\u0101unu"
    ],
    "ref": "N. <i>bha\u0303j\u0101unu</i> \u02bb to change (money) \u02bc; "
  },
  {
    "lang": "O\u1e5biy\u0101",
    "words": [
      "bha\u00f1jeib\u0101"
    ],
    "ref": "Or. <i>bha\u00f1jeib\u0101</i> \u02bb to cause to be broken or folded \u02bc; "
  },
  {
    "lang": "Hind\u012b",
    "words": [
      "bha\u0303j\u0101n\u0101"
    ],
    "ref": "H. <i>bha\u0303j\u0101n\u0101</i> \u02bb to change (money) \u02bc. -- See <smallcaps>bhajy\u00e1t\u0113</smallcaps>.<div>\u00a0\u00a0\t\t\t</div></body></html>"
  }
]