[
  {
    "lang": "Indo-Aryan",
    "words": "mandur\u0101\u02ca",
    "ref": "<html><body><number>9853</number> <b>mandur\u0101\u02ca</b><superscript>1</superscript> f. \u02bb stable \u02bc K\u0101lid., <i>mandura -- ja</i> -- \u02bb born in a stable (?) \u02bc Pat. [Cf. <i>mandup\u0101la</i> -- \u02bb groom \u02bc lex. &lt;-&gt; \u221a<smallcaps>mand</smallcaps><superscript>2</superscript>]"
  },
  {
    "lang": "Prakrit",
    "words": [
      "ma\u1e41dur\u0101"
    ],
    "ref": "Pk. <i>ma\u1e41dur\u0101</i> -- f. \u02bb horse stable \u02bc; "
  },
  {
    "lang": "Shina (\u1e62i\u1e47\u0101 \u2014 Dard.)",
    "words": [
      "m\u0103d\u016d\u0301r"
    ],
    "ref": "Sh. <i>m\u0103d\u016d\u0301r</i> f. \u02bb manger \u02bc; "
  },
  {
    "lang": "O\u1e5biy\u0101",
    "words": [
      "m\u0101dura"
    ],
    "ref": "Or. <i>m\u0101dura</i> \u02bb stable \u02bc.<div>\u00a0\u00a0\t\t\t</div></body></html>"
  }
]